[
  {
    "field": "id",
    "value": "https://www.logitechg.com/en-us/shop/p/pro-x2-superlight-wireless-mouse",
    "method": "ldjson",
    "keyPath": "@id",
    "identity_label": "possible",
    "identity_confidence": 0.75
  },
  {
    "field": "brand",
    "value": "Logitech G",
    "method": "ldjson",
    "keyPath": "brand",
    "evidenceRefs": [
      "sn_89f51bd789489d0d"
    ],
    "evidenceRefOrigin": "heuristic_snippet_match",
    "identity_label": "possible",
    "identity_confidence": 0.75
  },
  {
    "field": "model",
    "value": "PRO X SUPERLIGHT 2",
    "method": "ldjson",
    "keyPath": "name",
    "evidenceRefs": [
      "sn_f74b2303c1739014"
    ],
    "evidenceRefOrigin": "heuristic_snippet_match",
    "identity_label": "possible",
    "identity_confidence": 0.75
  },
  {
    "field": "id",
    "value": "pro-x2-superlight-wireless-mouse",
    "method": "ldjson",
    "keyPath": "productID",
    "evidenceRefs": [
      "sn_d14e6f9eff21c818"
    ],
    "evidenceRefOrigin": "heuristic_snippet_match",
    "identity_label": "possible",
    "identity_confidence": 0.75
  },
  {
    "field": "model",
    "value": "ProductModel",
    "method": "ldjson",
    "keyPath": "model[0].@type",
    "identity_label": "possible",
    "identity_confidence": 0.75
  },
  {
    "field": "model",
    "value": "PRO X SUPERLIGHT 2 - White",
    "method": "ldjson",
    "keyPath": "model[0].name",
    "identity_label": "possible",
    "identity_confidence": 0.75
  },
  {
    "field": "colors",
    "value": "White",
    "method": "ldjson",
    "keyPath": "model[0].color",
    "evidenceRefs": [
      "sn_6727aa72e39a7589"
    ],
    "evidenceRefOrigin": "heuristic_snippet_match",
    "identity_label": "possible",
    "identity_confidence": 0.75
  },
  {
    "field": "sku",
    "value": "910-006636",
    "method": "ldjson",
    "keyPath": "model[0].sku",
    "identity_label": "possible",
    "identity_confidence": 0.75
  },
  {
    "field": "model",
    "value": "910-006636",
    "method": "ldjson",
    "keyPath": "model[0].mpn",
    "identity_label": "possible",
    "identity_confidence": 0.75
  },
  {
    "field": "model",
    "value": "gaming-mice",
    "method": "ldjson",
    "keyPath": "model[0].category",
    "evidenceRefs": [
      "sn_f74b2303c1739014"
    ],
    "evidenceRefOrigin": "heuristic_snippet_match",
    "identity_label": "possible",
    "identity_confidence": 0.75
  },
  {
    "field": "model",
    "value": "https://resource.logitechg.com/c_fill,q_auto,f_auto,dpr_1.0/d_transparent.gif/content/dam/gaming/en/products/pro-x-superlight-2/new-gallery-assets-2025/pro-x-superlight-2-mice-top-angle-white-gallery-1.png,https://resource.logitechg.com/c_fill,q_auto,f_auto,dpr_1.0/d_transparent.gif/content/dam/gaming/en/products/pro-x-superlight-2/new-gallery-assets-2025/pro-x-superlight-2-mice-profile-left-angle-white-gallery-4.png,https://resource.logitechg.com/c_fill,q_auto,f_auto,dpr_1.0/d_transparent.gif/content/dam/gaming/en/products/pro-x-superlight-2/new-gallery-assets-2025/pro-x-superlight-2-mice-profile-right-angle-white-gallery-5.png,https://resource.logitechg.com/c_fill,q_auto,f_auto,dpr_1.0/d_transparent.gif/content/dam/gaming/en/products/pro-x-superlight-2/new-gallery-assets-2025/pro-x-superlight-2-mouse-bottom-angle-white-gallery-6.png,https://resource.logitechg.com/c_fill,q_auto,f_auto,dpr_1.0/d_transparent.gif/content/dam/gaming/en/products/pro-x-superlight-2/round-2/videocard-pro-x-superlight-2-gaming-mouse-desktop.png",
    "method": "ldjson",
    "keyPath": "model[0].image",
    "identity_label": "possible",
    "identity_confidence": 0.75
  },
  {
    "field": "model",
    "value": "Offer",
    "method": "ldjson",
    "keyPath": "model[0].offers.@type",
    "evidenceRefs": [
      "sn_b91285f3d95f9638"
    ],
    "evidenceRefOrigin": "heuristic_snippet_match",
    "identity_label": "possible",
    "identity_confidence": 0.75
  },
  {
    "field": "model",
    "value": "149.99",
    "method": "ldjson",
    "keyPath": "model[0].offers.price",
    "evidenceRefs": [
      "sn_6727aa72e39a7589"
    ],
    "evidenceRefOrigin": "heuristic_snippet_match",
    "identity_label": "possible",
    "identity_confidence": 0.75
  },
  {
    "field": "model",
    "value": "USD",
    "method": "ldjson",
    "keyPath": "model[0].offers.priceCurrency",
    "evidenceRefs": [
      "sn_89f51bd789489d0d"
    ],
    "evidenceRefOrigin": "heuristic_snippet_match",
    "identity_label": "possible",
    "identity_confidence": 0.75
  },
  {
    "field": "model",
    "value": "https://schema.org/InStock",
    "method": "ldjson",
    "keyPath": "model[0].offers.availability",
    "identity_label": "possible",
    "identity_confidence": 0.75
  },
  {
    "field": "model",
    "value": "UnitPriceSpecification",
    "method": "ldjson",
    "keyPath": "model[0].offers.priceSpecification.@type",
    "identity_label": "possible",
    "identity_confidence": 0.75
  },
  {
    "field": "model",
    "value": "https://schema.org/StrikethroughPrice",
    "method": "ldjson",
    "keyPath": "model[0].offers.priceSpecification.priceType",
    "identity_label": "possible",
    "identity_confidence": 0.75
  },
  {
    "field": "model",
    "value": "179.99",
    "method": "ldjson",
    "keyPath": "model[0].offers.priceSpecification.price",
    "evidenceRefs": [
      "sn_6727aa72e39a7589"
    ],
    "evidenceRefOrigin": "heuristic_snippet_match",
    "identity_label": "possible",
    "identity_confidence": 0.75
  },
  {
    "field": "model",
    "value": "USD",
    "method": "ldjson",
    "keyPath": "model[0].offers.priceSpecification.priceCurrency",
    "evidenceRefs": [
      "sn_89f51bd789489d0d"
    ],
    "evidenceRefOrigin": "heuristic_snippet_match",
    "identity_label": "possible",
    "identity_confidence": 0.75
  },
  {
    "field": "model",
    "value": "ProductModel",
    "method": "ldjson",
    "keyPath": "model[1].@type",
    "identity_label": "possible",
    "identity_confidence": 0.75
  },
  {
    "field": "model",
    "value": "PRO X SUPERLIGHT 2 - Black",
    "method": "ldjson",
    "keyPath": "model[1].name",
    "identity_label": "possible",
    "identity_confidence": 0.75
  },
  {
    "field": "colors",
    "value": "Black",
    "method": "ldjson",
    "keyPath": "model[1].color",
    "evidenceRefs": [
      "sn_d509682d057c5f67"
    ],
    "evidenceRefOrigin": "heuristic_snippet_match",
    "identity_label": "possible",
    "identity_confidence": 0.75
  },
  {
    "field": "sku",
    "value": "910-006628",
    "method": "ldjson",
    "keyPath": "model[1].sku",
    "evidenceRefs": [
      "sn_d2b8a3f95f41e058"
    ],
    "evidenceRefOrigin": "heuristic_snippet_match",
    "identity_label": "possible",
    "identity_confidence": 0.75
  },
  {
    "field": "model",
    "value": "910-006628",
    "method": "ldjson",
    "keyPath": "model[1].mpn",
    "evidenceRefs": [
      "sn_d2b8a3f95f41e058"
    ],
    "evidenceRefOrigin": "heuristic_snippet_match",
    "identity_label": "possible",
    "identity_confidence": 0.75
  },
  {
    "field": "model",
    "value": "gaming-mice",
    "method": "ldjson",
    "keyPath": "model[1].category",
    "evidenceRefs": [
      "sn_f74b2303c1739014"
    ],
    "evidenceRefOrigin": "heuristic_snippet_match",
    "identity_label": "possible",
    "identity_confidence": 0.75
  },
  {
    "field": "model",
    "value": "https://resource.logitechg.com/c_fill,q_auto,f_auto,dpr_1.0/d_transparent.gif/content/dam/gaming/en/products/pro-x-superlight-2/new-gallery-assets-2025/pro-x-superlight-2-mice-top-angle-black-gallery-1.png,https://resource.logitechg.com/c_fill,q_auto,f_auto,dpr_1.0/d_transparent.gif/content/dam/gaming/en/products/pro-x-superlight-2/new-gallery-assets-2025/pro-x-superlight-2-mice-profile-left-angle-black-gallery-4.png,https://resource.logitechg.com/c_fill,q_auto,f_auto,dpr_1.0/d_transparent.gif/content/dam/gaming/en/products/pro-x-superlight-2/new-gallery-assets-2025/pro-x-superlight-2-mice-profile-right-angle-black-gallery-5.png,https://resource.logitechg.com/c_fill,q_auto,f_auto,dpr_1.0/d_transparent.gif/content/dam/gaming/en/products/pro-x-superlight-2/new-gallery-assets-2025/pro-x-superlight-2-mice-bottom-angle-black-gallery-6.png,https://resource.logitechg.com/c_fill,q_auto,f_auto,dpr_1.0/d_transparent.gif/content/dam/gaming/en/products/pro-x-superlight-2/round-2/videocard-pro-x-superlight-2-gaming-mouse-desktop.png",
    "method": "ldjson",
    "keyPath": "model[1].image",
    "identity_label": "possible",
    "identity_confidence": 0.75
  },
  {
    "field": "model",
    "value": "Offer",
    "method": "ldjson",
    "keyPath": "model[1].offers.@type",
    "evidenceRefs": [
      "sn_b91285f3d95f9638"
    ],
    "evidenceRefOrigin": "heuristic_snippet_match",
    "identity_label": "possible",
    "identity_confidence": 0.75
  },
  {
    "field": "model",
    "value": "149.99",
    "method": "ldjson",
    "keyPath": "model[1].offers.price",
    "evidenceRefs": [
      "sn_6727aa72e39a7589"
    ],
    "evidenceRefOrigin": "heuristic_snippet_match",
    "identity_label": "possible",
    "identity_confidence": 0.75
  },
  {
    "field": "model",
    "value": "USD",
    "method": "ldjson",
    "keyPath": "model[1].offers.priceCurrency",
    "evidenceRefs": [
      "sn_89f51bd789489d0d"
    ],
    "evidenceRefOrigin": "heuristic_snippet_match",
    "identity_label": "possible",
    "identity_confidence": 0.75
  },
  {
    "field": "model",
    "value": "https://schema.org/InStock",
    "method": "ldjson",
    "keyPath": "model[1].offers.availability",
    "identity_label": "possible",
    "identity_confidence": 0.75
  },
  {
    "field": "model",
    "value": "UnitPriceSpecification",
    "method": "ldjson",
    "keyPath": "model[1].offers.priceSpecification.@type",
    "identity_label": "possible",
    "identity_confidence": 0.75
  },
  {
    "field": "model",
    "value": "https://schema.org/StrikethroughPrice",
    "method": "ldjson",
    "keyPath": "model[1].offers.priceSpecification.priceType",
    "identity_label": "possible",
    "identity_confidence": 0.75
  },
  {
    "field": "model",
    "value": "179.99",
    "method": "ldjson",
    "keyPath": "model[1].offers.priceSpecification.price",
    "evidenceRefs": [
      "sn_6727aa72e39a7589"
    ],
    "evidenceRefOrigin": "heuristic_snippet_match",
    "identity_label": "possible",
    "identity_confidence": 0.75
  },
  {
    "field": "model",
    "value": "USD",
    "method": "ldjson",
    "keyPath": "model[1].offers.priceSpecification.priceCurrency",
    "evidenceRefs": [
      "sn_89f51bd789489d0d"
    ],
    "evidenceRefOrigin": "heuristic_snippet_match",
    "identity_label": "possible",
    "identity_confidence": 0.75
  },
  {
    "field": "model",
    "value": "ProductModel",
    "method": "ldjson",
    "keyPath": "model[2].@type",
    "identity_label": "possible",
    "identity_confidence": 0.75
  },
  {
    "field": "model",
    "value": "PRO X SUPERLIGHT 2 - Pink",
    "method": "ldjson",
    "keyPath": "model[2].name",
    "identity_label": "possible",
    "identity_confidence": 0.75
  },
  {
    "field": "colors",
    "value": "Pink",
    "method": "ldjson",
    "keyPath": "model[2].color",
    "identity_label": "possible",
    "identity_confidence": 0.75
  },
  {
    "field": "sku",
    "value": "910-006795",
    "method": "ldjson",
    "keyPath": "model[2].sku",
    "identity_label": "possible",
    "identity_confidence": 0.75
  },
  {
    "field": "model",
    "value": "910-006795",
    "method": "ldjson",
    "keyPath": "model[2].mpn",
    "identity_label": "possible",
    "identity_confidence": 0.75
  },
  {
    "field": "model",
    "value": "gaming-mice",
    "method": "ldjson",
    "keyPath": "model[2].category",
    "evidenceRefs": [
      "sn_f74b2303c1739014"
    ],
    "evidenceRefOrigin": "heuristic_snippet_match",
    "identity_label": "possible",
    "identity_confidence": 0.75
  },
  {
    "field": "model",
    "value": "https://resource.logitechg.com/c_fill,q_auto,f_auto,dpr_1.0/d_transparent.gif/content/dam/gaming/en/products/pro-x-superlight-2/new-gallery-assets-2025/pro-x-superlight-2-mice-top-angle-pink-gallery-1-new.png,https://resource.logitechg.com/c_fill,q_auto,f_auto,dpr_1.0/d_transparent.gif/content/dam/gaming/en/products/pro-x-superlight-2/new-gallery-assets-2025/pro-x-superlight-2-mouse-profile-left-angle-pink-gallery-4-new.png,https://resource.logitechg.com/c_fill,q_auto,f_auto,dpr_1.0/d_transparent.gif/content/dam/gaming/en/products/pro-x-superlight-2/new-gallery-assets-2025/pro-x-superlight-2-mouse-profile-right-angle-pink-gallery-5-new.png,https://resource.logitechg.com/c_fill,q_auto,f_auto,dpr_1.0/d_transparent.gif/content/dam/gaming/en/products/pro-x-superlight-2/new-gallery-assets-2025/pro-x-superlight-2-mouse-bottom-angle-pink-gallery-6-new.png,https://resource.logitechg.com/c_fill,q_auto,f_auto,dpr_1.0/d_transparent.gif/content/dam/gaming/en/products/pro-x-superlight-2/round-2/videocard-pro-x-superlight-2-gaming-mouse-desktop.png",
    "method": "ldjson",
    "keyPath": "model[2].image",
    "identity_label": "possible",
    "identity_confidence": 0.75
  },
  {
    "field": "model",
    "value": "Offer",
    "method": "ldjson",
    "keyPath": "model[2].offers.@type",
    "evidenceRefs": [
      "sn_b91285f3d95f9638"
    ],
    "evidenceRefOrigin": "heuristic_snippet_match",
    "identity_label": "possible",
    "identity_confidence": 0.75
  },
  {
    "field": "model",
    "value": "149.99",
    "method": "ldjson",
    "keyPath": "model[2].offers.price",
    "evidenceRefs": [
      "sn_6727aa72e39a7589"
    ],
    "evidenceRefOrigin": "heuristic_snippet_match",
    "identity_label": "possible",
    "identity_confidence": 0.75
  },
  {
    "field": "model",
    "value": "USD",
    "method": "ldjson",
    "keyPath": "model[2].offers.priceCurrency",
    "evidenceRefs": [
      "sn_89f51bd789489d0d"
    ],
    "evidenceRefOrigin": "heuristic_snippet_match",
    "identity_label": "possible",
    "identity_confidence": 0.75
  },
  {
    "field": "model",
    "value": "https://schema.org/InStock",
    "method": "ldjson",
    "keyPath": "model[2].offers.availability",
    "identity_label": "possible",
    "identity_confidence": 0.75
  },
  {
    "field": "model",
    "value": "UnitPriceSpecification",
    "method": "ldjson",
    "keyPath": "model[2].offers.priceSpecification.@type",
    "identity_label": "possible",
    "identity_confidence": 0.75
  },
  {
    "field": "model",
    "value": "https://schema.org/StrikethroughPrice",
    "method": "ldjson",
    "keyPath": "model[2].offers.priceSpecification.priceType",
    "identity_label": "possible",
    "identity_confidence": 0.75
  },
  {
    "field": "model",
    "value": "179.99",
    "method": "ldjson",
    "keyPath": "model[2].offers.priceSpecification.price",
    "evidenceRefs": [
      "sn_6727aa72e39a7589"
    ],
    "evidenceRefOrigin": "heuristic_snippet_match",
    "identity_label": "possible",
    "identity_confidence": 0.75
  },
  {
    "field": "model",
    "value": "USD",
    "method": "ldjson",
    "keyPath": "model[2].offers.priceSpecification.priceCurrency",
    "evidenceRefs": [
      "sn_89f51bd789489d0d"
    ],
    "evidenceRefOrigin": "heuristic_snippet_match",
    "identity_label": "possible",
    "identity_confidence": 0.75
  },
  {
    "field": "model",
    "value": "Logitech G",
    "method": "ldjson",
    "keyPath": "itemListElement[0].item.name",
    "evidenceRefs": [
      "sn_f74b2303c1739014"
    ],
    "evidenceRefOrigin": "heuristic_snippet_match",
    "identity_label": "possible",
    "identity_confidence": 0.75
  },
  {
    "field": "id",
    "value": "https://www.logitechg.com/en-us",
    "method": "ldjson",
    "keyPath": "itemListElement[0].item.@id",
    "evidenceRefs": [
      "sn_4ff921b71ef3e693"
    ],
    "evidenceRefOrigin": "heuristic_snippet_match",
    "identity_label": "possible",
    "identity_confidence": 0.75
  },
  {
    "field": "model",
    "value": "Products - Logitech",
    "method": "ldjson",
    "keyPath": "itemListElement[1].item.name",
    "identity_label": "possible",
    "identity_confidence": 0.75
  },
  {
    "field": "id",
    "value": "https://www.logitechg.com/en-us/shop",
    "method": "ldjson",
    "keyPath": "itemListElement[1].item.@id",
    "evidenceRefs": [
      "sn_4ff921b71ef3e693"
    ],
    "evidenceRefOrigin": "heuristic_snippet_match",
    "identity_label": "possible",
    "identity_confidence": 0.75
  },
  {
    "field": "model",
    "value": "Products",
    "method": "ldjson",
    "keyPath": "itemListElement[2].item.name",
    "evidenceRefs": [
      "sn_f74b2303c1739014"
    ],
    "evidenceRefOrigin": "heuristic_snippet_match",
    "identity_label": "possible",
    "identity_confidence": 0.75
  },
  {
    "field": "id",
    "value": "https://www.logitechg.com/en-us/shop/c/gaming-mice",
    "method": "ldjson",
    "keyPath": "itemListElement[2].item.@id",
    "identity_label": "possible",
    "identity_confidence": 0.75
  },
  {
    "field": "model",
    "value": "PRO X SUPERLIGHT 2",
    "method": "ldjson",
    "keyPath": "itemListElement[3].item.name",
    "evidenceRefs": [
      "sn_f74b2303c1739014"
    ],
    "evidenceRefOrigin": "heuristic_snippet_match",
    "identity_label": "possible",
    "identity_confidence": 0.75
  },
  {
    "field": "id",
    "value": "https://www.logitechg.com/en-us/shop/p/pro-x2-superlight-wireless-mouse",
    "method": "ldjson",
    "keyPath": "itemListElement[3].item.@id",
    "identity_label": "possible",
    "identity_confidence": 0.75
  },
  {
    "field": "model",
    "value": "Daniel",
    "method": "ldjson",
    "keyPath": "review[0].author.name",
    "evidenceRefs": [
      "sn_d2b8a3f95f41e058"
    ],
    "evidenceRefOrigin": "heuristic_snippet_match",
    "identity_label": "possible",
    "identity_confidence": 0.75
  },
  {
    "field": "model",
    "value": "Anonymous",
    "method": "ldjson",
    "keyPath": "review[1].author.name",
    "identity_label": "possible",
    "identity_confidence": 0.75
  },
  {
    "field": "model",
    "value": "Danny mclovin",
    "method": "ldjson",
    "keyPath": "review[2].author.name",
    "identity_label": "possible",
    "identity_confidence": 0.75
  },
  {
    "field": "model",
    "value": "Bobby",
    "method": "ldjson",
    "keyPath": "review[3].author.name",
    "identity_label": "possible",
    "identity_confidence": 0.75
  },
  {
    "field": "model",
    "value": "David",
    "method": "ldjson",
    "keyPath": "review[4].author.name",
    "identity_label": "possible",
    "identity_confidence": 0.75
  },
  {
    "field": "model",
    "value": "Anonymous",
    "method": "ldjson",
    "keyPath": "review[5].author.name",
    "identity_label": "possible",
    "identity_confidence": 0.75
  },
  {
    "field": "model",
    "value": "Jose",
    "method": "ldjson",
    "keyPath": "review[6].author.name",
    "identity_label": "possible",
    "identity_confidence": 0.75
  },
  {
    "field": "model",
    "value": "Greeeee",
    "method": "ldjson",
    "keyPath": "review[7].author.name",
    "identity_label": "possible",
    "identity_confidence": 0.75
  },
  {
    "field": "model",
    "value": "https://photos-us.bazaarvoice.com/photo/2/cGhvdG86bG9naXRlY2gtaW5j/8a98c232-9931-53ad-83c3-5de9a2e47745",
    "method": "ldjson",
    "keyPath": "review[7].image[0].thumbnail.name",
    "identity_label": "possible",
    "identity_confidence": 0.75
  },
  {
    "field": "model",
    "value": "https://photos-us.bazaarvoice.com/photo/2/cGhvdG86bG9naXRlY2gtaW5j/8f3532cc-6987-531b-b7fc-05dc70bc6e2b",
    "method": "ldjson",
    "keyPath": "review[7].image[1].thumbnail.name",
    "identity_label": "possible",
    "identity_confidence": 0.75
  }
]